pluserable/__init__.py
pluserable/actions.py
pluserable/configuration.py
pluserable/const.py
pluserable/data/__init__.py
pluserable/data/models.py
pluserable/data/repository.py
pluserable/data/sqlalchemy/__init__.py
pluserable/data/sqlalchemy/models.py
pluserable/data/sqlalchemy/repository.py
pluserable/data/typing.py
pluserable/events.py
pluserable/exceptions.py
pluserable/forms.py
pluserable/httpexceptions.py
pluserable/interfaces.py
pluserable/no_bruteforce.py
pluserable/schemas.py
pluserable/strings.py
pluserable/templates/admin/create_user.mako
pluserable/templates/admin/index.mako
pluserable/templates/admin/users_index.mako
pluserable/templates/edit_profile.mako
pluserable/templates/forgot_password.mako
pluserable/templates/layout.mako
pluserable/templates/login.mako
pluserable/templates/profile.mako
pluserable/templates/register.mako
pluserable/templates/reset_password.mako
pluserable/web/__init__.py
pluserable/web/pyramid/__init__.py
pluserable/web/pyramid/demo.py
pluserable/web/pyramid/resources.py
pluserable/web/pyramid/security.py
pluserable/web/pyramid/typing.py
pluserable/web/pyramid/views.py
pluserable-0.11.0.dist-info/WHEEL
pluserable-0.11.0.dist-info/METADATA
pluserable-0.11.0.dist-info/RECORD
