Metadata-Version: 2.1
Name: pluserable
Version: 0.11.0
Summary: Generic user registration for the Pyramid web framework
Home-page: https://github.com/nandoflorestan/pluserable
License: BSD
Keywords: authentication,horus,pyramid,user,registration
Author: Nando Florestan
Author-email: nandoflorestan@gmail.com
Requires-Python: >=3.9
Classifier: Development Status :: 5 - Production/Stable
Classifier: Intended Audience :: Developers
Classifier: License :: OSI Approved :: BSD License
Classifier: License :: Other/Proprietary License
Classifier: Operating System :: OS Independent
Classifier: Programming Language :: Python
Classifier: Programming Language :: Python :: 3
Classifier: Programming Language :: Python :: 3.9
Classifier: Programming Language :: Python :: 3.10
Classifier: Programming Language :: Python :: 3
Classifier: Programming Language :: Python :: 3.10
Classifier: Programming Language :: Python :: 3.11
Classifier: Programming Language :: Python :: 3.9
Classifier: Programming Language :: Python :: Implementation :: CPython
Classifier: Programming Language :: Python :: Implementation :: PyPy
Classifier: Topic :: Internet :: WWW/HTTP :: Dynamic Content
Classifier: Topic :: Software Development :: Libraries :: Python Modules
Requires-Dist: bag (>=5.0.0)
Requires-Dist: deform
Requires-Dist: kerno (>=0.7.0)
Requires-Dist: passlib
Requires-Dist: pyramid (>=2.0)
Requires-Dist: pyramid_mailer
Requires-Dist: pyramid_mako
Requires-Dist: redis
Requires-Dist: sqlalchemy
Requires-Dist: transaction
Requires-Dist: zope.interface
Project-URL: Documentation, http://docs.nando.audio/pluserable/latest/
Project-URL: Repository, https://github.com/nandoflorestan/pluserable
